pyselfmongo/__init__.py
pyselfmongo/py_self_mongo.py
pyselfmongo-0.1.0.dist-info/LICENSE
pyselfmongo-0.1.0.dist-info/WHEEL
pyselfmongo-0.1.0.dist-info/METADATA
pyselfmongo-0.1.0.dist-info/RECORD
