Metadata-Version: 2.1
Name: pyselfmongo
Version: 0.1.0
Summary: A PySelfMongo client for the [MongoDB][mongo] database is a thin client that connects to a mongo server and provides a simple interface to the database. A client is written as a singleton to make sure that only one connection is open at a time. The connection timeout is taken care by checking the server info every time a request is made. A new connection is made if the server info is not available or the connection has timed out.
Home-page: https://github.com/Aarif1430/PySelfMongo
License: MIT
Keywords: mongo,mongodb,client,self,singleton,connection,timeout
Author: Aarif1430
Author-email: malikarif13@gmail.com
Requires-Python: >=3.10,<4.0
Classifier: License :: OSI Approved :: MIT License
Classifier: Programming Language :: Python :: 3
Classifier: Programming Language :: Python :: 3.10
Requires-Dist: pymongo (>=4.1.0,<5.0.0)
